{"frames":[{"filename":"sprite3","frame":{"x":376,"y":52,"w":42,"h":53},"rotated":false,"trimmed":false,"spriteSourceSize":{"x":0,"y":0,"w":42,"h":53},"sourceSize":{"w":42,"h":53}},{"filename":"sprite4","frame":{"x":537,"y":52,"w":42,"h":44},"rotated":false,"trimmed":false,"spriteSourceSize":{"x":0,"y":0,"w":42,"h":44},"sourceSize":{"w":42,"h":44}},{"filename":"sprite2","frame":{"x":217,"y":53,"w":40,"h":52},"rotated":false,"trimmed":false,"spriteSourceSize":{"x":0,"y":0,"w":40,"h":52},"sourceSize":{"w":40,"h":52}},{"filename":"sprite7","frame":{"x":1016,"y":53,"w":41,"h":52},"rotated":false,"trimmed":false,"spriteSourceSize":{"x":0,"y":0,"w":41,"h":52},"sourceSize":{"w":41,"h":52}},{"filename":"sprite8","frame":{"x":1177,"y":53,"w":40,"h":46},"rotated":false,"trimmed":false,"spriteSourceSize":{"x":0,"y":0,"w":40,"h":46},"sourceSize":{"w":40,"h":46}},{"filename":"sprite6","frame":{"x":856,"y":54,"w":41,"h":51},"rotated":false,"trimmed":false,"spriteSourceSize":{"x":0,"y":0,"w":41,"h":51},"sourceSize":{"w":41,"h":51}},{"filename":"sprite1","frame":{"x":58,"y":55,"w":39,"h":50},"rotated":false,"trimmed":false,"spriteSourceSize":{"x":0,"y":0,"w":39,"h":50},"sourceSize":{"w":39,"h":50}},{"filename":"sprite5","frame":{"x":692,"y":55,"w":45,"h":50},"rotated":false,"trimmed":false,"spriteSourceSize":{"x":0,"y":0,"w":45,"h":50},"sourceSize":{"w":45,"h":50}}],"meta":{"app":"https://www.leshylabs.com/apps/sstool/","version":"Leshy SpriteSheet Tool v0.8.4","image":"spritesheet.png","size":{"w":1280,"h":111},"scale":1}}